house_prices_nguyen_nguyen/__init__.py
house_prices_nguyen_nguyen/inference.py
house_prices_nguyen_nguyen/preprocess.py
house_prices_nguyen_nguyen/train.py
house_prices_nguyen_nguyen-0.0.6.dist-info/METADATA
house_prices_nguyen_nguyen-0.0.6.dist-info/WHEEL
house_prices_nguyen_nguyen-0.0.6.dist-info/licenses/LICENSE
house_prices_nguyen_nguyen-0.0.6.dist-info/RECORD
