Metadata-Version: 2.4
Name: house_prices_nguyen_nguyen
Version: 0.0.6
Summary: Package to predict house prices
Project-URL: Homepage, https://github.com/NHNguyen94/dsp-nguyen-nguyen
Project-URL: Issues, https://github.com/NHNguyen94/dsp-nguyen-nguyen/issues
Author-email: Nguyen NGUYEN <nguyenhainguyen2606@gmail.com>
License-Expression: MIT
License-File: LICENSE
Classifier: Operating System :: OS Independent
Classifier: Programming Language :: Python :: 3
Requires-Python: >=3.9
